python_usernames/__about__.py
python_usernames/__init__.py
python_usernames/reserved_words.py
python_usernames/validators.py
python_usernames/words.txt
python_usernames-1.1.0.dist-info/METADATA
python_usernames-1.1.0.dist-info/WHEEL
python_usernames-1.1.0.dist-info/RECORD
