Metadata-Version: 2.4
Name: python-usernames
Version: 1.1.0
Summary: Python library to validate usernames suitable for use in public facing applications.
Project-URL: Documentation, https://github.com/theskumar/python-usernames/tree/main#readme
Project-URL: Source, https://github.com/theskumar/python-usernames
Project-URL: Tracker, https://github.com/theskumar/python-usernames/issues
Author-email: Saurabh Kumar <python-usernames@saurabh-kumar.com>
License-Expression: MIT
Keywords: regex,safe,security,signup,user registration,username,validation
Classifier: Development Status :: 4 - Beta
Classifier: Intended Audience :: Developers
Classifier: Intended Audience :: System Administrators
Classifier: License :: OSI Approved :: MIT License
Classifier: Operating System :: OS Independent
Classifier: Programming Language :: Python
Classifier: Programming Language :: Python :: 3.8
Classifier: Programming Language :: Python :: 3.9
Classifier: Programming Language :: Python :: 3.10
Classifier: Programming Language :: Python :: 3.11
Classifier: Programming Language :: Python :: 3.12
Classifier: Programming Language :: Python :: 3.13
Classifier: Programming Language :: Python :: 3.14
Classifier: Topic :: Security
Classifier: Topic :: Utilities
Requires-Python: >=3.8
